{
	"File": {
		"__typename": "FileMatch",
		"repository": {
			"name": "github.com/jdegre/5GC_APIs"
		},
		"file": {
			"name": "TS24558_Eecs_ServiceProvisioning.yaml",
			"size": 0,
			"path": "TS24558_Eecs_ServiceProvisioning.yaml",
			"byteSize": 18455,
			"content": "openapi: 3.0.0\ninfo:\n  title: Eecs_ServiceProvisioning\n  description: |\n    API for ECS Service Provisioning.\n    © 2022, 3GPP Organizational Partners (ARIB, ATIS, CCSA, ETSI, TSDSI, TTA, TTC).\n    All rights reserved.\n  version: \"1.0.0-alpha.3\"\nexternalDocs:\n  description: 3GPP TS 24.558 V1.2.0 Enabling Edge Applications; Protocol specification.\n  url: https://www.3gpp.org/ftp/Specs/archive/24_series/24.558/\nsecurity:\n  - {}\n  - oAuth2ClientCredentials: []\nservers:\n  - url: '{apiRoot}/eecs-serviceprovisioning/v1'\n    variables:\n      apiRoot:\n        default: https://example.com\n        description: apiRoot as defined in clause 7.5 of 3GPP TS 29.558\npaths:\n  /subscriptions:\n    post:\n      description: Creates a new subscription in ECS in order to be notified of provisioning data changes of interest.\n      tags:\n        - Service Provisioning Subscriptions\n      requestBody:\n        required: true\n        content:\n          application/json:\n            schema:\n              $ref: '#/components/schemas/ECSServProvSubscription'\n      callbacks:\n        notificationDestination:\n          '{request.body#/notificationDestination}':\n            post:\n              requestBody:  # contents of the callback message\n                required: true\n                content:\n                  application/json:\n                    schema:\n                      $ref: '#/components/schemas/ServProvNotification'\n              responses:\n                '204':\n                  description: No Content (successful notification)\n                '307':\n                  $ref: 'TS29122_CommonData.yaml#/components/responses/307'\n                '308':\n                  $ref: 'TS29122_CommonData.yaml#/components/responses/308'\n                '400':\n                  $ref: 'TS29122_CommonData.yaml#/components/responses/400'\n                '401':\n                  $ref: 'TS29122_CommonData.yaml#/components/responses/401'\n                '403':\n                  $ref: 'TS29122_CommonData.yaml#/components/responses/403'\n                '404':\n                  $ref: 'TS29122_CommonData.yaml#/components/responses/404'\n                '411':\n                  $ref: 'TS29122_CommonData.yaml#/components/responses/411'\n                '413':\n                  $ref: 'TS29122_CommonData.yaml#/components/responses/413'\n                '415':\n                  $ref: 'TS29122_CommonData.yaml#/components/responses/415'\n                '429':\n                  $ref: 'TS29122_CommonData.yaml#/components/responses/429'\n                '500':\n                  $ref: 'TS29122_CommonData.yaml#/components/responses/500'\n                '503':\n                  $ref: 'TS29122_CommonData.yaml#/components/responses/503'\n                default:\n                  $ref: 'TS29122_CommonData.yaml#/components/responses/default'\n      responses:\n        '201':\n          description: Individual ECS Service Provisioning Subscription resource created successfully.\n          content:\n            application/json:\n              schema:\n                $ref: '#/components/schemas/ECSServProvSubscription'\n          headers:\n            Location:\n              description: 'Contains the URI of the newly created resource'\n              required: true\n              schema:\n                type: string\n        '400':\n          $ref: 'TS29122_CommonData.yaml#/components/responses/400'\n        '401':\n          $ref: 'TS29122_CommonData.yaml#/components/responses/401'\n        '403':\n          $ref: 'TS29122_CommonData.yaml#/components/responses/403'\n        '404':\n          $ref: 'TS29122_CommonData.yaml#/components/responses/404'\n        '411':\n          $ref: 'TS29122_CommonData.yaml#/components/responses/411'\n        '413':\n          $ref: 'TS29122_CommonData.yaml#/components/responses/413'\n        '415':\n          $ref: 'TS29122_CommonData.yaml#/components/responses/415'\n        '429':\n          $ref: 'TS29122_CommonData.yaml#/components/responses/429'\n        '500':\n          $ref: 'TS29122_CommonData.yaml#/components/responses/500'\n        '503':\n          $ref: 'TS29122_CommonData.yaml#/components/responses/503'\n        default:\n          $ref: 'TS29122_CommonData.yaml#/components/responses/default'\n\n  /subscriptions/{subscriptionId}:\n    put:\n      description: Updates an existing individual service provisioning subscription identified by the subscriptionId.\n      tags:\n        - Individual Service Provisioning Subscription\n      parameters:\n        - name: subscriptionId\n          in: path\n          description: Identifies an individual service provisioning subscription\n          required: true\n          schema:\n            type: string\n      requestBody:\n        description: Parameters to replace the existing subscription\n        required: true\n        content:\n          application/json:\n            schema:\n              $ref: '#/components/schemas/ECSServProvSubscription'\n      responses:\n        '200':\n          description: OK (The individual service provisioning subscription matching the subscriptionId was modified successfully)\n          content:\n            application/json:\n              schema:\n                $ref: '#/components/schemas/ECSServProvSubscription'\n        '400':\n          $ref: 'TS29122_CommonData.yaml#/components/responses/400'\n        '401':\n          $ref: 'TS29122_CommonData.yaml#/components/responses/401'\n        '403':\n          $ref: 'TS29122_CommonData.yaml#/components/responses/403'\n        '404':\n          $ref: 'TS29122_CommonData.yaml#/components/responses/404'\n        '411':\n          $ref: 'TS29122_CommonData.yaml#/components/responses/411'\n        '413':\n          $ref: 'TS29122_CommonData.yaml#/components/responses/413'\n        '415':\n          $ref: 'TS29122_CommonData.yaml#/components/responses/415'\n        '429':\n          $ref: 'TS29122_CommonData.yaml#/components/responses/429'\n        '500':\n          $ref: 'TS29122_CommonData.yaml#/components/responses/500'\n        '503':\n          $ref: 'TS29122_CommonData.yaml#/components/responses/503'\n        default:\n          $ref: 'TS29122_CommonData.yaml#/components/responses/default'\n\n    delete:\n      description: Deletes an existing individual service provisioning subscription identified by the subscriptionId.\n      tags:\n        - Individual Service Provisioning Subscription\n      parameters:\n        - name: subscriptionId\n          in: path\n          description: Identifies an individual service provisioning subscription\n          required: true\n          schema:\n            type: string\n      responses:\n        '204':\n          description: The individual service provisioning subscription matching the subscriptionId is deleted.\n        '307':\n          $ref: 'TS29122_CommonData.yaml#/components/responses/307'\n        '308':\n          $ref: 'TS29122_CommonData.yaml#/components/responses/308'\n        '400':\n          $ref: 'TS29122_CommonData.yaml#/components/responses/400'\n        '401':\n          $ref: 'TS29122_CommonData.yaml#/components/responses/401'\n        '403':\n          $ref: 'TS29122_CommonData.yaml#/components/responses/403'\n        '404':\n          $ref: 'TS29122_CommonData.yaml#/components/responses/404'\n        '429':\n          $ref: 'TS29122_CommonData.yaml#/components/responses/429'\n        '500':\n          $ref: 'TS29122_CommonData.yaml#/components/responses/500'\n        '503':\n          $ref: 'TS29122_CommonData.yaml#/components/responses/503'\n        default:\n          $ref: 'TS29122_CommonData.yaml#/components/responses/default'\n    patch:\n      description: Partially updates an existing individual service provisioning subscription identified by the subscriptionId.\n      tags:\n        - Individual Service Provisioning Subscription\n      parameters:\n        - name: subscriptionId\n          in: path\n          description: Identifies an individual service provisioning subscription\n          required: true\n          schema:\n            type: string\n      requestBody:\n        description: Parameters to replace the existing subscription\n        required: true\n        content:\n          application/json:\n            schema:\n              $ref: '#/components/schemas/ECSServProvSubscriptionPatch'\n      responses:\n        '200':\n          description: OK (The individual service provisioning subscription matching the subscriptionId was modified successfully)\n          content:\n            application/json:\n              schema:\n                $ref: '#/components/schemas/ECSServProvSubscription'\n        '400':\n          $ref: 'TS29122_CommonData.yaml#/components/responses/400'\n        '401':\n          $ref: 'TS29122_CommonData.yaml#/components/responses/401'\n        '403':\n          $ref: 'TS29122_CommonData.yaml#/components/responses/403'\n        '404':\n          $ref: 'TS29122_CommonData.yaml#/components/responses/404'\n        '411':\n          $ref: 'TS29122_CommonData.yaml#/components/responses/411'\n        '413':\n          $ref: 'TS29122_CommonData.yaml#/components/responses/413'\n        '415':\n          $ref: 'TS29122_CommonData.yaml#/components/responses/415'\n        '429':\n          $ref: 'TS29122_CommonData.yaml#/components/responses/429'\n        '500':\n          $ref: 'TS29122_CommonData.yaml#/components/responses/500'\n        '503':\n          $ref: 'TS29122_CommonData.yaml#/components/responses/503'\n        default:\n          $ref: 'TS29122_CommonData.yaml#/components/responses/default'\n\n  /request:\n    post:\n      summary: Request service provisioning information.\n      operationId: RequestServProv\n      tags:\n        - Request Service Provisioning\n      requestBody:\n        required: true\n        content:\n          application/json:\n            schema:\n              $ref: '#/components/schemas/ECSServProvReq'\n      responses:\n        '200':\n          description: OK (The requested service provisioning information was returned successfully).\n          content:\n            application/json:\n              schema:\n                $ref: '#/components/schemas/ECSServProvResp'\n        '204':\n          description: No Content (the requested service provisioning information does not exist).\n        '400':\n          $ref: 'TS29122_CommonData.yaml#/components/responses/400'\n        '401':\n          $ref: 'TS29122_CommonData.yaml#/components/responses/401'\n        '403':\n          $ref: 'TS29122_CommonData.yaml#/components/responses/403'\n        '404':\n          $ref: 'TS29122_CommonData.yaml#/components/responses/404'\n        '411':\n          $ref: 'TS29122_CommonData.yaml#/components/responses/411'\n        '413':\n          $ref: 'TS29122_CommonData.yaml#/components/responses/413'\n        '415':\n          $ref: 'TS29122_CommonData.yaml#/components/responses/415'\n        '429':\n          $ref: 'TS29122_CommonData.yaml#/components/responses/429'\n        '500':\n          $ref: 'TS29122_CommonData.yaml#/components/responses/500'\n        '503':\n          $ref: 'TS29122_CommonData.yaml#/components/responses/503'\n        default:\n          $ref: 'TS29122_CommonData.yaml#/components/responses/default'\n\ncomponents:\n  securitySchemes:\n    oAuth2ClientCredentials:\n      type: oauth2\n      flows:\n        clientCredentials:\n          tokenUrl: '{tokenUrl}'\n          scopes: {}\n  schemas:\n    ECSServProvReq:\n      description: ECS service provisioning request information.\n      type: object\n      properties:\n        eecId:\n          type: string\n          description: Represents a unique identifier of the EEC.\n        ueId:\n          $ref: 'TS29571_CommonData.yaml#/components/schemas/Gpsi'\n        # acProfs:\n          # type: array\n          # items:\n            # $ref: \n          # description: Information about services the EEC wants to connect to.\n        # eecSvcContSupp:\n          # type: array\n          # items:\n            # $ref: 'TS29558_CommonData.yaml#/components/schemas/ACRScenario'\n          # description: Indicates if the EEC supports service continuity or not, also indicates which ACR scenarios are supported by the EEC.\n        connInfo:\n          type: array\n          items:\n            $ref: '#/components/schemas/ConnectivityInfo'\n          description: List of connectivity information for the UE.\n        locInf:\n          $ref: 'TS29122_MonitoringEvent.yaml#/components/schemas/LocationInfo'\n      required:\n        - eecId\n    ECSServProvResp:\n      description: ECS service provisioning response information.\n      type: object\n      properties:\n        ednCnfgInfo:\n          type: array\n          items:\n            $ref: '#/components/schemas/EDNConfigInfo'\n          minItems: 1\n          description: List of EDN configuration information.\n      required:\n        - ednCnfgInfo\n    ECSServProvSubscription:\n      description: Represents an individual service provisioning subscription resource.\n      type: object\n      properties:\n        eecId:\n          type: string\n          description: Represents a unique identifier of the EEC.\n        ueId:\n          $ref: 'TS29571_CommonData.yaml#/components/schemas/Gpsi'\n        # acProfs:\n          # type: array\n          # items:\n            # $ref: \n          # description: Information about services the EEC wants to connect to.\n        expTime:\n          $ref: 'TS29122_CommonData.yaml#/components/schemas/DateTime'\n        # eecSvcContSupp:\n          # type: array\n          # items:\n            # $ref: 'TS29558_CommonData.yaml#/components/schemas/ACRScenario'\n          # description: Indicates if the EEC supports service continuity or not, also indicates which ACR scenarios are supported by the EEC.\n        connInfo:\n          type: array\n          items:\n            $ref: '#/components/schemas/ConnectivityInfo'\n          description: List of connectivity information for the UE.\n        notificationDestination:\n          $ref: 'TS29122_CommonData.yaml#/components/schemas/Uri'\n        requestTestNotification:\n          type: boolean\n          description: Set to true by Subscriber to request the ECS to send a test notification. Set to false or omitted otherwise.\n        websockNotifConfig:\n          $ref: 'TS29122_CommonData.yaml#/components/schemas/WebsockNotifConfig'\n        suppFeat:\n          $ref: 'TS29571_CommonData.yaml#/components/schemas/SupportedFeatures'\n      required:\n        - eecId\n    ServProvNotification:\n      description: Represents notification information of a service provisioning Event.\n      type: object\n      properties:\n        subId:\n          type: string\n          description: Identifier of the individual service provisioning subscription for which the service provisioning notification is delivered.\n        ednCnfgInfo:\n          type: array\n          items:\n            $ref: '#/components/schemas/EDNConfigInfo'\n          minItems: 1\n          description: List of EDN configuration information.\n      required:\n        - subId\n        - ednCnfgInfo\n    ConnectivityInfo:\n      description: Represents the connectivity information for the UE.\n      type: object\n      properties:\n        plmnId:\n          $ref: 'TS29571_CommonData.yaml#/components/schemas/PlmnId'\n        ssId:\n          type: string\n          description: Identifies the SSID of the access point to which the UE is attached.\n    EDNConfigInfo:\n      description: Represents the EDN information.\n      type: object\n      properties:\n        ednConInfo:\n          $ref: '#/components/schemas/EDNConInfo'\n        eess:\n          type: array\n          items:\n            $ref: '#/components/schemas/EESInfo'\n          minItems: 1\n          description: Contains the list of EESs of the EDN.\n        lifeTime:\n          $ref: 'TS29122_CommonData.yaml#/components/schemas/DateTime'\n      required:\n        - ednConInfo\n        - eess\n    EDNConInfo:\n      description: Represents an EDN connection information .\n      type: object\n      properties:\n        dnn:\n          $ref: 'TS29571_CommonData.yaml#/components/schemas/Dnn'\n        snssai:\n          $ref: 'TS29571_CommonData.yaml#/components/schemas/Snssai'\n        ednTopoSrvArea:\n          $ref: 'TS29122_CommonData.yaml#/components/schemas/LocationArea5G'\n    EESInfo:\n      description: Represents EES information.\n      type: object\n      properties:\n        eesId:\n          type: string\n          description: Identity of the EES\n        # endPt:\n          # $ref: 'TS29558_CommonData.yaml#/components/schemas/EndPoint' \n          # description: Endpoint information (e.g. URI, FQDN, IP address) used to communicate with the EES.\n        easIds:\n          type: array\n          items:\n            type: string\n          description: Identities of the Edge Application Servers registered with the EES.\n        ecspInfo:\n          type: string\n          description: Represents an ECSP Information.\n        svcArea:\n          $ref: 'TS29122_CommonData.yaml#/components/schemas/LocationArea5G'\n        dnais:\n          type: array\n          items:\n            $ref: 'TS29571_CommonData.yaml#/components/schemas/Dnai'\n          description: Represents list of Data network access identifier.\n        # eesSvcContSupp:\n          # type: array\n          # items:\n            # $ref: 'TS29558_CommonData.yaml#/components/schemas/ACRScenario'\n          # description: Indicates if the EES supports service continuity or not, also indicates which ACR scenarios are supported by the EES.\n        eecRegConf:\n          type: boolean\n          description: Indicates whether the EEC is required to register on the EES to use edge services or not.\n      required:\n        - eesId\n        - eecRegConf\n    ECSServProvSubscriptionPatch:\n      description: Represents an individual service provisioning subscription resource.\n      type: object\n      properties:\n        acProfs:\n          type: array\n          items:\n            $ref: 'TS24558_Eees_EECRegistration.yaml#/components/schemas/ACProfile'\n          description: Information about services the EEC wants to connect to.\n        expTime:\n          $ref: 'TS29122_CommonData.yaml#/components/schemas/DateTime'\n        eecSvcContSupp:\n          type: array\n          items:\n            $ref: 'TS29558_Eecs_EESRegistration.yaml#/components/schemas/ACRScenario'\n          description: Indicates if the EEC supports service continuity or not, also indicates which ACR scenarios are supported by the EEC.\n        connInfo:\n          type: array\n          items:\n            $ref: '#/components/schemas/ConnectivityInfo'\n          description: List of connectivity information for the UE.\n",
			"canonicalURL": "/github.com/jdegre/5GC_APIs@156cf6056495fbf2f1e81b2b9574ba6369f91640/-/blob/TS24558_Eecs_ServiceProvisioning.yaml",
			"externalURLs": [
				{
					"url": "https://github.com/jdegre/5GC_APIs/blob/156cf6056495fbf2f1e81b2b9574ba6369f91640/TS24558_Eecs_ServiceProvisioning.yaml",
					"serviceKind": "GITHUB"
				}
			]
		}
	},
	"Error": "parse: parse spec: parse components: schemas: \"ConnectivityInfo\": parse schema: property \"plmnId\": parse schema: resolve \"TS29571_CommonData.yaml#/components/schemas/PlmnId\": external \"TS29571_CommonData.yaml\": file: local file reference is not allowed"
}