{
	"File": {
		"__typename": "FileMatch",
		"repository": {
			"name": "github.com/aml-org/als"
		},
		"file": {
			"name": "content-example.yaml",
			"size": 0,
			"path": "als-suggestions/shared/src/test/resources/test/oas30/by-directory/yaml/open-api-document/paths/path-object/operation/responses/content/content-example.yaml",
			"byteSize": 346,
			"content": "openapi: 3.0.0\npaths:\n  /:\n    get:\n      responses:\n        '200':\n          content:\n            application/json:\n              schema:\n                type: object\n                properties:\n                  a:\n                    type: string\n                  b:\n                    type: integer\n              example:\n                *\n"
		}
	},
	"Error": "invalidYAML: yaml: line 17: did not find expected alphabetic or numeric character"
}