{
	"File": {
		"__typename": "FileMatch",
		"repository": {
			"name": "github.com/organization-supply/organization.supply"
		},
		"file": {
			"name": "api.yml",
			"size": 0,
			"path": "hugo/content/api.yml",
			"byteSize": 19316,
			"content": "openapi: 3.0.2\ninfo:\n  title: Organization.supply REST API\n  version: ''\n  description: Documentation for the REST API for Organization.supply\npaths:\n  /{organization}/api/products:\n    get:\n      operationId: listProducts\n      parameters:\n      - name: organization\n        in: path\n        required: true\n        description: ''\n        schema:\n          type: string\n      responses:\n        '200':\n          content:\n            application/json:\n              schema:\n                type: array\n                items:\n                  properties:\n                    id:\n                      type: string\n                      format: uuid\n                      readOnly: true\n                    name:\n                      type: string\n                      maxLength: 200\n                    desc:\n                      type: string\n                    image:\n                      type: string\n                      readOnly: true\n                    price_cost:\n                      type: number\n                    price_sale:\n                      type: number\n                    tags:\n                      type: array\n                      items:\n                        type: string\n                      readOnly: true\n                  required:\n                  - name\n          description: ''\n    post:\n      operationId: CreateProduct\n      parameters:\n      - name: organization\n        in: path\n        required: true\n        description: ''\n        schema:\n          type: string\n      requestBody:\n        content:\n          application/json:\n            schema:\n              properties:\n                name:\n                  type: string\n                  maxLength: 200\n                desc:\n                  type: string\n                price_cost:\n                  type: number\n                price_sale:\n                  type: number\n              required:\n              - name\n      responses:\n        '200':\n          content:\n            application/json:\n              schema:\n                properties:\n                  id:\n                    type: string\n                    format: uuid\n                    readOnly: true\n                  name:\n                    type: string\n                    maxLength: 200\n                  desc:\n                    type: string\n                  image:\n                    type: string\n                    readOnly: true\n                  price_cost:\n                    type: number\n                  price_sale:\n                    type: number\n                  tags:\n                    type: array\n                    items:\n                      type: string\n                    readOnly: true\n                required:\n                - name\n          description: ''\n  /{organization}/api/products/{id}:\n    get:\n      operationId: RetrieveProduct\n      parameters:\n      - name: id\n        in: path\n        required: true\n        description: ''\n        schema:\n          type: string\n      - name: organization\n        in: path\n        required: true\n        description: ''\n        schema:\n          type: string\n      responses:\n        '200':\n          content:\n            application/json:\n              schema:\n                properties:\n                  id:\n                    type: string\n                    format: uuid\n                    readOnly: true\n                  name:\n                    type: string\n                    maxLength: 200\n                  desc:\n                    type: string\n                  image:\n                    type: string\n                    readOnly: true\n                  price_cost:\n                    type: number\n                  price_sale:\n                    type: number\n                  tags:\n                    type: array\n                    items:\n                      type: string\n                    readOnly: true\n                required:\n                - name\n          description: ''\n    put:\n      operationId: UpdateProduct\n      parameters:\n      - name: id\n        in: path\n        required: true\n        description: ''\n        schema:\n          type: string\n      - name: organization\n        in: path\n        required: true\n        description: ''\n        schema:\n          type: string\n      requestBody:\n        content:\n          application/json:\n            schema:\n              properties:\n                name:\n                  type: string\n                  maxLength: 200\n                desc:\n                  type: string\n                price_cost:\n                  type: number\n                price_sale:\n                  type: number\n              required:\n              - name\n      responses:\n        '200':\n          content:\n            application/json:\n              schema:\n                properties:\n                  id:\n                    type: string\n                    format: uuid\n                    readOnly: true\n                  name:\n                    type: string\n                    maxLength: 200\n                  desc:\n                    type: string\n                  image:\n                    type: string\n                    readOnly: true\n                  price_cost:\n                    type: number\n                  price_sale:\n                    type: number\n                  tags:\n                    type: array\n                    items:\n                      type: string\n                    readOnly: true\n                required:\n                - name\n          description: ''\n    patch:\n      operationId: PartialUpdateProduct\n      parameters:\n      - name: id\n        in: path\n        required: true\n        description: ''\n        schema:\n          type: string\n      - name: organization\n        in: path\n        required: true\n        description: ''\n        schema:\n          type: string\n      requestBody:\n        content:\n          application/json:\n            schema:\n              properties:\n                name:\n                  type: string\n                  maxLength: 200\n                desc:\n                  type: string\n                price_cost:\n                  type: number\n                price_sale:\n                  type: number\n      responses:\n        '200':\n          content:\n            application/json:\n              schema:\n                properties:\n                  id:\n                    type: string\n                    format: uuid\n                    readOnly: true\n                  name:\n                    type: string\n                    maxLength: 200\n                  desc:\n                    type: string\n                  image:\n                    type: string\n                    readOnly: true\n                  price_cost:\n                    type: number\n                  price_sale:\n                    type: number\n                  tags:\n                    type: array\n                    items:\n                      type: string\n                    readOnly: true\n                required:\n                - name\n          description: ''\n    delete:\n      operationId: DestroyProduct\n      parameters:\n      - name: id\n        in: path\n        required: true\n        description: ''\n        schema:\n          type: string\n      - name: organization\n        in: path\n        required: true\n        description: ''\n        schema:\n          type: string\n      responses:\n        '204':\n          description: ''\n  /{organization}/api/locations:\n    get:\n      operationId: listLocations\n      parameters:\n      - name: organization\n        in: path\n        required: true\n        description: ''\n        schema:\n          type: string\n      responses:\n        '200':\n          content:\n            application/json:\n              schema:\n                type: array\n                items:\n                  properties:\n                    id:\n                      type: string\n                      format: uuid\n                      readOnly: true\n                    name:\n                      type: string\n                      maxLength: 200\n                    image:\n                      type: string\n                      readOnly: true\n                    desc:\n                      type: string\n                    size:\n                      type: number\n                    tags:\n                      type: array\n                      items:\n                        type: string\n                      readOnly: true\n                  required:\n                  - name\n          description: ''\n    post:\n      operationId: CreateLocation\n      parameters:\n      - name: organization\n        in: path\n        required: true\n        description: ''\n        schema:\n          type: string\n      requestBody:\n        content:\n          application/json:\n            schema:\n              properties:\n                name:\n                  type: string\n                  maxLength: 200\n                desc:\n                  type: string\n                size:\n                  type: number\n              required:\n              - name\n      responses:\n        '200':\n          content:\n            application/json:\n              schema:\n                properties:\n                  id:\n                    type: string\n                    format: uuid\n                    readOnly: true\n                  name:\n                    type: string\n                    maxLength: 200\n                  image:\n                    type: string\n                    readOnly: true\n                  desc:\n                    type: string\n                  size:\n                    type: number\n                  tags:\n                    type: array\n                    items:\n                      type: string\n                    readOnly: true\n                required:\n                - name\n          description: ''\n  /{organization}/api/locations/{id}:\n    get:\n      operationId: RetrieveLocation\n      parameters:\n      - name: id\n        in: path\n        required: true\n        description: ''\n        schema:\n          type: string\n      - name: organization\n        in: path\n        required: true\n        description: ''\n        schema:\n          type: string\n      responses:\n        '200':\n          content:\n            application/json:\n              schema:\n                properties:\n                  id:\n                    type: string\n                    format: uuid\n                    readOnly: true\n                  name:\n                    type: string\n                    maxLength: 200\n                  image:\n                    type: string\n                    readOnly: true\n                  desc:\n                    type: string\n                  size:\n                    type: number\n                  tags:\n                    type: array\n                    items:\n                      type: string\n                    readOnly: true\n                required:\n                - name\n          description: ''\n    put:\n      operationId: UpdateLocation\n      parameters:\n      - name: id\n        in: path\n        required: true\n        description: ''\n        schema:\n          type: string\n      - name: organization\n        in: path\n        required: true\n        description: ''\n        schema:\n          type: string\n      requestBody:\n        content:\n          application/json:\n            schema:\n              properties:\n                name:\n                  type: string\n                  maxLength: 200\n                desc:\n                  type: string\n                size:\n                  type: number\n              required:\n              - name\n      responses:\n        '200':\n          content:\n            application/json:\n              schema:\n                properties:\n                  id:\n                    type: string\n                    format: uuid\n                    readOnly: true\n                  name:\n                    type: string\n                    maxLength: 200\n                  image:\n                    type: string\n                    readOnly: true\n                  desc:\n                    type: string\n                  size:\n                    type: number\n                  tags:\n                    type: array\n                    items:\n                      type: string\n                    readOnly: true\n                required:\n                - name\n          description: ''\n    patch:\n      operationId: PartialUpdateLocation\n      parameters:\n      - name: id\n        in: path\n        required: true\n        description: ''\n        schema:\n          type: string\n      - name: organization\n        in: path\n        required: true\n        description: ''\n        schema:\n          type: string\n      requestBody:\n        content:\n          application/json:\n            schema:\n              properties:\n                name:\n                  type: string\n                  maxLength: 200\n                desc:\n                  type: string\n                size:\n                  type: number\n      responses:\n        '200':\n          content:\n            application/json:\n              schema:\n                properties:\n                  id:\n                    type: string\n                    format: uuid\n                    readOnly: true\n                  name:\n                    type: string\n                    maxLength: 200\n                  image:\n                    type: string\n                    readOnly: true\n                  desc:\n                    type: string\n                  size:\n                    type: number\n                  tags:\n                    type: array\n                    items:\n                      type: string\n                    readOnly: true\n                required:\n                - name\n          description: ''\n    delete:\n      operationId: DestroyLocation\n      parameters:\n      - name: id\n        in: path\n        required: true\n        description: ''\n        schema:\n          type: string\n      - name: organization\n        in: path\n        required: true\n        description: ''\n        schema:\n          type: string\n      responses:\n        '204':\n          description: ''\n  /{organization}/api/inventory:\n    get:\n      operationId: listInventorys\n      parameters:\n      - name: organization\n        in: path\n        required: true\n        description: ''\n        schema:\n          type: string\n      responses:\n        '200':\n          content:\n            application/json:\n              schema:\n                type: array\n                items:\n                  properties:\n                    id:\n                      type: string\n                      format: uuid\n                      readOnly: true\n                    product:\n                      type: string\n                    location:\n                      type: string\n                    amount:\n                      type: number\n                  required:\n                  - product\n                  - location\n          description: ''\n  /{organization}/api/mutations:\n    get:\n      operationId: listMutations\n      parameters:\n      - name: organization\n        in: path\n        required: true\n        description: ''\n        schema:\n          type: string\n      responses:\n        '200':\n          content:\n            application/json:\n              schema:\n                type: array\n                items:\n                  properties:\n                    id:\n                      type: string\n                      format: uuid\n                      readOnly: true\n                    amount:\n                      type: number\n                    product:\n                      type: string\n                    location:\n                      type: string\n                    desc:\n                      type: string\n                    operation:\n                      enum:\n                      - add\n                      - remove\n                      - reserved\n                  required:\n                  - amount\n                  - product\n                  - location\n          description: ''\n    post:\n      operationId: CreateMutation\n      parameters:\n      - name: organization\n        in: path\n        required: true\n        description: ''\n        schema:\n          type: string\n      requestBody:\n        content:\n          application/json:\n            schema:\n              properties:\n                amount:\n                  type: number\n                product:\n                  type: string\n                location:\n                  type: string\n                desc:\n                  type: string\n                operation:\n                  enum:\n                  - add\n                  - remove\n                  - reserved\n              required:\n              - amount\n              - product\n              - location\n      responses:\n        '200':\n          content:\n            application/json:\n              schema:\n                properties:\n                  id:\n                    type: string\n                    format: uuid\n                    readOnly: true\n                  amount:\n                    type: number\n                  product:\n                    type: string\n                  location:\n                    type: string\n                  desc:\n                    type: string\n                  operation:\n                    enum:\n                    - add\n                    - remove\n                    - reserved\n                required:\n                - amount\n                - product\n                - location\n          description: ''\n  /{organization}/api/me:\n    get:\n      operationId: RetrieveUser\n      parameters:\n      - name: organization\n        in: path\n        required: true\n        description: ''\n        schema:\n          type: string\n      responses:\n        '200':\n          content:\n            application/json:\n              schema:\n                properties:\n                  id:\n                    type: string\n                    format: uuid\n                    readOnly: true\n                  email:\n                    type: string\n                    format: email\n                    maxLength: 254\n                  name:\n                    type: string\n                    maxLength: 255\n                required:\n                - email\n          description: ''\n  /{organization}/api/notifications:\n    get:\n      operationId: listNotifications\n      parameters:\n      - name: organization\n        in: path\n        required: true\n        description: ''\n        schema:\n          type: string\n      responses:\n        '200':\n          content:\n            application/json:\n              schema:\n                type: array\n                items:\n                  properties:\n                    id:\n                      type: integer\n                      readOnly: true\n                    timestamp:\n                      type: string\n                      format: date-time\n                    description:\n                      type: string\n                      nullable: true\n                    verb:\n                      type: string\n                      maxLength: 255\n                  required:\n                  - verb\n          description: ''\n",
			"canonicalURL": "/github.com/organization-supply/organization.supply@4a9fcf3ebaaa5bf712bb93a9f8b7062801d2ef72/-/blob/hugo/content/api.yml",
			"externalURLs": [
				{
					"url": "https://github.com/organization-supply/organization.supply/blob/4a9fcf3ebaaa5bf712bb93a9f8b7062801d2ef72/hugo/content/api.yml",
					"serviceKind": "GITHUB"
				}
			]
		}
	}
}